netbox_field_permissions/__init__.py
netbox_field_permissions/constants.py
netbox_field_permissions/forms.py
netbox_field_permissions/migrations/0001_initial.py
netbox_field_permissions/migrations/__init__.py
netbox_field_permissions/models.py
netbox_field_permissions/navigation.py
netbox_field_permissions/tables.py
netbox_field_permissions/templates/netbox_field_permissions/fieldpermission.html
netbox_field_permissions/templates/netbox_field_permissions/fieldpermission_edit.html
netbox_field_permissions/templates/netbox_field_permissions/fieldpermission_list.html
netbox_field_permissions/templates/netbox_field_permissions/manage.html
netbox_field_permissions/urls.py
netbox_field_permissions/utilities.py
netbox_field_permissions/validators.py
netbox_field_permissions/views.py
netbox_field_permissions-0.1.0rc2.dist-info/LICENSE
netbox_field_permissions-0.1.0rc2.dist-info/METADATA
netbox_field_permissions-0.1.0rc2.dist-info/WHEEL
netbox_field_permissions-0.1.0rc2.dist-info/RECORD
