Metadata-Version: 2.1
Name: netbox-field-permissions
Version: 0.1.0rc2
Summary: NetBox plugin that provides permissions on object fields.
Home-page: https://github.com/TheDJVG/netbox-field-permissions
Keywords: netbox,permissions
Author: Daan van Gorkum
Author-email: me+netbox@dj.vg
Requires-Python: >=3.11,<4.0
Classifier: Programming Language :: Python :: 3
Classifier: Programming Language :: Python :: 3.11
Classifier: Programming Language :: Python :: 3.12
Project-URL: Repository, https://github.com/TheDJVG/netbox-field-permissions
